kaggle_extractor/__init__.py
kaggle_extractor/main.py
kaggle_extractor-0.2.dist-info/METADATA
kaggle_extractor-0.2.dist-info/WHEEL
kaggle_extractor-0.2.dist-info/top_level.txt
kaggle_extractor-0.2.dist-info/RECORD
