Metadata-Version: 2.1
Name: kaggle-extractor
Version: 0.2
Requires-Dist: kaggle
